<?xml version="1.0"?>
<AllProjectProperties>
	<ProjectProperties>
		<Class>Project</Class>
		<Name>WelcomeToVide</Name>
		<ProjectName>WelcomeToVide</ProjectName>
		<DirectoryName></DirectoryName>
		<Path>projects</Path>
		<MainFile>C1Main.asm</MainFile>
		<Description></Description>
		<Version>1.0</Version>
		<Author>Malban</Author>
		<Bankswitching>none</Bankswitching>
		<createBankswitchCode>false</createBankswitchCode>
		<createGameLoopCode>false</createGameLoopCode>
		<NumberOfBanks>1</NumberOfBanks>
		<BankMainFiless>
			<BankMainFiles>C1Main.asm</BankMainFiles>
		</BankMainFiless>
		<Extras>1024</Extras>
		<ProjectPreScriptClass></ProjectPreScriptClass>
		<ProjectPreScriptName></ProjectPreScriptName>
		<ProjectPostScriptClass></ProjectPostScriptClass>
		<ProjectPostScriptName></ProjectPostScriptName>
		<BankDefiness>
			<BankDefines></BankDefines>
		</BankDefiness>
		<WheelName></WheelName>
	</ProjectProperties>
</AllProjectProperties>
