<VectorAnimation>
<isAnimation>
false</isAnimation>
<GFXVectorList>
<id>
3987</id>
<order>
0</order>
<GFXVector>
<startVertex>
<x>
-37.0</x>
<y>
129.0</y>
<z>
0.0</z>
<w>
1.0</w>
<use_x>
true</use_x>
<use_y>
true</use_y>
<use_z>
true</use_z>
<use_w>
true</use_w>
<id>
667029</id>
</startVertex>
<endVertex>
<x>
-37.0</x>
<y>
57.0</y>
<z>
0.0</z>
<w>
1.0</w>
<use_x>
true</use_x>
<use_y>
true</use_y>
<use_z>
true</use_z>
<use_w>
true</use_w>
<id>
667030</id>
</endVertex>
<pattern>
255</pattern>
<r>
255</r>
<g>
255</g>
<b>
255</b>
<a>
254</a>
<id>
89266</id>
<order>
0</order>
<start_neighbour_id>
-1</start_neighbour_id>
<end_neighbour_id>
89267</end_neighbour_id>
<start_is_relative>
false</start_is_relative>
<end_is_relative>
false</end_is_relative>
<is_3d>
false</is_3d>
<intensity>
127</intensity>
</GFXVector>
<GFXVector>
<startVertex>
<x>
-37.0</x>
<y>
57.0</y>
<z>
0.0</z>
<w>
1.0</w>
<use_x>
true</use_x>
<use_y>
true</use_y>
<use_z>
true</use_z>
<use_w>
true</use_w>
<id>
667030</id>
</startVertex>
<endVertex>
<x>
-17.0</x>
<y>
20.0</y>
<z>
0.0</z>
<w>
1.0</w>
<use_x>
true</use_x>
<use_y>
true</use_y>
<use_z>
true</use_z>
<use_w>
true</use_w>
<id>
667032</id>
</endVertex>
<pattern>
255</pattern>
<r>
255</r>
<g>
0</g>
<b>
255</b>
<a>
254</a>
<id>
89267</id>
<order>
1</order>
<start_neighbour_id>
89266</start_neighbour_id>
<end_neighbour_id>
89268</end_neighbour_id>
<start_is_relative>
true</start_is_relative>
<end_is_relative>
true</end_is_relative>
<is_3d>
false</is_3d>
<intensity>
127</intensity>
</GFXVector>
<GFXVector>
<startVertex>
<x>
-17.0</x>
<y>
20.0</y>
<z>
0.0</z>
<w>
1.0</w>
<use_x>
true</use_x>
<use_y>
true</use_y>
<use_z>
true</use_z>
<use_w>
true</use_w>
<id>
667032</id>
</startVertex>
<endVertex>
<x>
-15.0</x>
<y>
37.0</y>
<z>
0.0</z>
<w>
1.0</w>
<use_x>
true</use_x>
<use_y>
true</use_y>
<use_z>
true</use_z>
<use_w>
true</use_w>
<id>
667034</id>
</endVertex>
<pattern>
255</pattern>
<r>
255</r>
<g>
0</g>
<b>
255</b>
<a>
254</a>
<id>
89268</id>
<order>
2</order>
<start_neighbour_id>
89267</start_neighbour_id>
<end_neighbour_id>
89269</end_neighbour_id>
<start_is_relative>
true</start_is_relative>
<end_is_relative>
true</end_is_relative>
<is_3d>
false</is_3d>
<intensity>
127</intensity>
</GFXVector>
<GFXVector>
<startVertex>
<x>
-15.0</x>
<y>
37.0</y>
<z>
0.0</z>
<w>
1.0</w>
<use_x>
true</use_x>
<use_y>
true</use_y>
<use_z>
true</use_z>
<use_w>
true</use_w>
<id>
667034</id>
</startVertex>
<endVertex>
<x>
-7.0</x>
<y>
19.0</y>
<z>
0.0</z>
<w>
1.0</w>
<use_x>
true</use_x>
<use_y>
true</use_y>
<use_z>
true</use_z>
<use_w>
true</use_w>
<id>
667036</id>
</endVertex>
<pattern>
255</pattern>
<r>
255</r>
<g>
0</g>
<b>
255</b>
<a>
254</a>
<id>
89269</id>
<order>
3</order>
<start_neighbour_id>
89268</start_neighbour_id>
<end_neighbour_id>
89270</end_neighbour_id>
<start_is_relative>
true</start_is_relative>
<end_is_relative>
true</end_is_relative>
<is_3d>
false</is_3d>
<intensity>
127</intensity>
</GFXVector>
<GFXVector>
<startVertex>
<x>
-7.0</x>
<y>
19.0</y>
<z>
0.0</z>
<w>
1.0</w>
<use_x>
true</use_x>
<use_y>
true</use_y>
<use_z>
true</use_z>
<use_w>
true</use_w>
<id>
667036</id>
</startVertex>
<endVertex>
<x>
15.0</x>
<y>
15.0</y>
<z>
0.0</z>
<w>
1.0</w>
<use_x>
true</use_x>
<use_y>
true</use_y>
<use_z>
true</use_z>
<use_w>
true</use_w>
<id>
667038</id>
</endVertex>
<pattern>
255</pattern>
<r>
255</r>
<g>
0</g>
<b>
255</b>
<a>
254</a>
<id>
89270</id>
<order>
4</order>
<start_neighbour_id>
89269</start_neighbour_id>
<end_neighbour_id>
89271</end_neighbour_id>
<start_is_relative>
true</start_is_relative>
<end_is_relative>
true</end_is_relative>
<is_3d>
false</is_3d>
<intensity>
127</intensity>
</GFXVector>
<GFXVector>
<startVertex>
<x>
15.0</x>
<y>
15.0</y>
<z>
0.0</z>
<w>
1.0</w>
<use_x>
true</use_x>
<use_y>
true</use_y>
<use_z>
true</use_z>
<use_w>
true</use_w>
<id>
667038</id>
</startVertex>
<endVertex>
<x>
31.0</x>
<y>
17.0</y>
<z>
0.0</z>
<w>
1.0</w>
<use_x>
true</use_x>
<use_y>
true</use_y>
<use_z>
true</use_z>
<use_w>
true</use_w>
<id>
667040</id>
</endVertex>
<pattern>
255</pattern>
<r>
255</r>
<g>
0</g>
<b>
255</b>
<a>
254</a>
<id>
89271</id>
<order>
5</order>
<start_neighbour_id>
89270</start_neighbour_id>
<end_neighbour_id>
89272</end_neighbour_id>
<start_is_relative>
true</start_is_relative>
<end_is_relative>
true</end_is_relative>
<is_3d>
false</is_3d>
<intensity>
127</intensity>
</GFXVector>
<GFXVector>
<startVertex>
<x>
31.0</x>
<y>
17.0</y>
<z>
0.0</z>
<w>
1.0</w>
<use_x>
true</use_x>
<use_y>
true</use_y>
<use_z>
true</use_z>
<use_w>
true</use_w>
<id>
667040</id>
</startVertex>
<endVertex>
<x>
46.0</x>
<y>
33.0</y>
<z>
0.0</z>
<w>
1.0</w>
<use_x>
true</use_x>
<use_y>
true</use_y>
<use_z>
true</use_z>
<use_w>
true</use_w>
<id>
667042</id>
</endVertex>
<pattern>
255</pattern>
<r>
255</r>
<g>
0</g>
<b>
255</b>
<a>
254</a>
<id>
89272</id>
<order>
6</order>
<start_neighbour_id>
89271</start_neighbour_id>
<end_neighbour_id>
89273</end_neighbour_id>
<start_is_relative>
true</start_is_relative>
<end_is_relative>
true</end_is_relative>
<is_3d>
false</is_3d>
<intensity>
127</intensity>
</GFXVector>
<GFXVector>
<startVertex>
<x>
46.0</x>
<y>
33.0</y>
<z>
0.0</z>
<w>
1.0</w>
<use_x>
true</use_x>
<use_y>
true</use_y>
<use_z>
true</use_z>
<use_w>
true</use_w>
<id>
667042</id>
</startVertex>
<endVertex>
<x>
39.0</x>
<y>
-3.0</y>
<z>
0.0</z>
<w>
1.0</w>
<use_x>
true</use_x>
<use_y>
true</use_y>
<use_z>
true</use_z>
<use_w>
true</use_w>
<id>
667044</id>
</endVertex>
<pattern>
255</pattern>
<r>
255</r>
<g>
0</g>
<b>
255</b>
<a>
254</a>
<id>
89273</id>
<order>
7</order>
<start_neighbour_id>
89272</start_neighbour_id>
<end_neighbour_id>
89274</end_neighbour_id>
<start_is_relative>
true</start_is_relative>
<end_is_relative>
true</end_is_relative>
<is_3d>
false</is_3d>
<intensity>
127</intensity>
</GFXVector>
<GFXVector>
<startVertex>
<x>
39.0</x>
<y>
-3.0</y>
<z>
0.0</z>
<w>
1.0</w>
<use_x>
true</use_x>
<use_y>
true</use_y>
<use_z>
true</use_z>
<use_w>
true</use_w>
<id>
667044</id>
</startVertex>
<endVertex>
<x>
15.0</x>
<y>
1.0</y>
<z>
0.0</z>
<w>
1.0</w>
<use_x>
true</use_x>
<use_y>
true</use_y>
<use_z>
true</use_z>
<use_w>
true</use_w>
<id>
667046</id>
</endVertex>
<pattern>
255</pattern>
<r>
255</r>
<g>
0</g>
<b>
255</b>
<a>
254</a>
<id>
89274</id>
<order>
8</order>
<start_neighbour_id>
89273</start_neighbour_id>
<end_neighbour_id>
89275</end_neighbour_id>
<start_is_relative>
true</start_is_relative>
<end_is_relative>
true</end_is_relative>
<is_3d>
false</is_3d>
<intensity>
127</intensity>
</GFXVector>
<GFXVector>
<startVertex>
<x>
15.0</x>
<y>
1.0</y>
<z>
0.0</z>
<w>
1.0</w>
<use_x>
true</use_x>
<use_y>
true</use_y>
<use_z>
true</use_z>
<use_w>
true</use_w>
<id>
667046</id>
</startVertex>
<endVertex>
<x>
-15.0</x>
<y>
-3.0</y>
<z>
0.0</z>
<w>
1.0</w>
<use_x>
true</use_x>
<use_y>
true</use_y>
<use_z>
true</use_z>
<use_w>
true</use_w>
<id>
667048</id>
</endVertex>
<pattern>
255</pattern>
<r>
255</r>
<g>
0</g>
<b>
255</b>
<a>
254</a>
<id>
89275</id>
<order>
9</order>
<start_neighbour_id>
89274</start_neighbour_id>
<end_neighbour_id>
89276</end_neighbour_id>
<start_is_relative>
true</start_is_relative>
<end_is_relative>
true</end_is_relative>
<is_3d>
false</is_3d>
<intensity>
127</intensity>
</GFXVector>
<GFXVector>
<startVertex>
<x>
-15.0</x>
<y>
-3.0</y>
<z>
0.0</z>
<w>
1.0</w>
<use_x>
true</use_x>
<use_y>
true</use_y>
<use_z>
true</use_z>
<use_w>
true</use_w>
<id>
667048</id>
</startVertex>
<endVertex>
<x>
-60.0</x>
<y>
46.0</y>
<z>
0.0</z>
<w>
1.0</w>
<use_x>
true</use_x>
<use_y>
true</use_y>
<use_z>
true</use_z>
<use_w>
true</use_w>
<id>
667050</id>
</endVertex>
<pattern>
255</pattern>
<r>
255</r>
<g>
0</g>
<b>
255</b>
<a>
254</a>
<id>
89276</id>
<order>
10</order>
<start_neighbour_id>
89275</start_neighbour_id>
<end_neighbour_id>
89277</end_neighbour_id>
<start_is_relative>
true</start_is_relative>
<end_is_relative>
true</end_is_relative>
<is_3d>
false</is_3d>
<intensity>
127</intensity>
</GFXVector>
<GFXVector>
<startVertex>
<x>
-60.0</x>
<y>
46.0</y>
<z>
0.0</z>
<w>
1.0</w>
<use_x>
true</use_x>
<use_y>
true</use_y>
<use_z>
true</use_z>
<use_w>
true</use_w>
<id>
667050</id>
</startVertex>
<endVertex>
<x>
-79.0</x>
<y>
55.0</y>
<z>
0.0</z>
<w>
1.0</w>
<use_x>
true</use_x>
<use_y>
true</use_y>
<use_z>
true</use_z>
<use_w>
true</use_w>
<id>
667052</id>
</endVertex>
<pattern>
255</pattern>
<r>
255</r>
<g>
0</g>
<b>
255</b>
<a>
254</a>
<id>
89277</id>
<order>
11</order>
<start_neighbour_id>
89276</start_neighbour_id>
<end_neighbour_id>
89278</end_neighbour_id>
<start_is_relative>
true</start_is_relative>
<end_is_relative>
true</end_is_relative>
<is_3d>
false</is_3d>
<intensity>
127</intensity>
</GFXVector>
<GFXVector>
<startVertex>
<x>
-79.0</x>
<y>
55.0</y>
<z>
0.0</z>
<w>
1.0</w>
<use_x>
true</use_x>
<use_y>
true</use_y>
<use_z>
true</use_z>
<use_w>
true</use_w>
<id>
667052</id>
</startVertex>
<endVertex>
<x>
-62.0</x>
<y>
60.0</y>
<z>
0.0</z>
<w>
1.0</w>
<use_x>
true</use_x>
<use_y>
true</use_y>
<use_z>
true</use_z>
<use_w>
true</use_w>
<id>
667054</id>
</endVertex>
<pattern>
255</pattern>
<r>
255</r>
<g>
255</g>
<b>
255</b>
<a>
254</a>
<id>
89278</id>
<order>
12</order>
<start_neighbour_id>
89277</start_neighbour_id>
<end_neighbour_id>
-1</end_neighbour_id>
<start_is_relative>
false</start_is_relative>
<end_is_relative>
false</end_is_relative>
<is_3d>
false</is_3d>
<intensity>
127</intensity>
</GFXVector>
</GFXVectorList>
<GFXVectorList>
<id>
3988</id>
<order>
2</order>
<GFXVector>
<startVertex>
<x>
37.0</x>
<y>
26.0</y>
<z>
0.0</z>
<w>
1.0</w>
<use_x>
true</use_x>
<use_y>
true</use_y>
<use_z>
true</use_z>
<use_w>
true</use_w>
<id>
667055</id>
</startVertex>
<endVertex>
<x>
33.0</x>
<y>
37.0</y>
<z>
0.0</z>
<w>
1.0</w>
<use_x>
true</use_x>
<use_y>
true</use_y>
<use_z>
true</use_z>
<use_w>
true</use_w>
<id>
667056</id>
</endVertex>
<pattern>
255</pattern>
<r>
255</r>
<g>
255</g>
<b>
255</b>
<a>
254</a>
<id>
89279</id>
<order>
0</order>
<start_neighbour_id>
-1</start_neighbour_id>
<end_neighbour_id>
89280</end_neighbour_id>
<start_is_relative>
false</start_is_relative>
<end_is_relative>
false</end_is_relative>
<is_3d>
false</is_3d>
<intensity>
127</intensity>
</GFXVector>
<GFXVector>
<startVertex>
<x>
33.0</x>
<y>
37.0</y>
<z>
0.0</z>
<w>
1.0</w>
<use_x>
true</use_x>
<use_y>
true</use_y>
<use_z>
true</use_z>
<use_w>
true</use_w>
<id>
667056</id>
</startVertex>
<endVertex>
<x>
49.0</x>
<y>
46.0</y>
<z>
0.0</z>
<w>
1.0</w>
<use_x>
true</use_x>
<use_y>
true</use_y>
<use_z>
true</use_z>
<use_w>
true</use_w>
<id>
667058</id>
</endVertex>
<pattern>
255</pattern>
<r>
255</r>
<g>
0</g>
<b>
255</b>
<a>
254</a>
<id>
89280</id>
<order>
1</order>
<start_neighbour_id>
89279</start_neighbour_id>
<end_neighbour_id>
89281</end_neighbour_id>
<start_is_relative>
true</start_is_relative>
<end_is_relative>
true</end_is_relative>
<is_3d>
false</is_3d>
<intensity>
127</intensity>
</GFXVector>
<GFXVector>
<startVertex>
<x>
49.0</x>
<y>
46.0</y>
<z>
0.0</z>
<w>
1.0</w>
<use_x>
true</use_x>
<use_y>
true</use_y>
<use_z>
true</use_z>
<use_w>
true</use_w>
<id>
667058</id>
</startVertex>
<endVertex>
<x>
39.0</x>
<y>
50.0</y>
<z>
0.0</z>
<w>
1.0</w>
<use_x>
true</use_x>
<use_y>
true</use_y>
<use_z>
true</use_z>
<use_w>
true</use_w>
<id>
667060</id>
</endVertex>
<pattern>
255</pattern>
<r>
255</r>
<g>
0</g>
<b>
255</b>
<a>
254</a>
<id>
89281</id>
<order>
2</order>
<start_neighbour_id>
89280</start_neighbour_id>
<end_neighbour_id>
89282</end_neighbour_id>
<start_is_relative>
true</start_is_relative>
<end_is_relative>
true</end_is_relative>
<is_3d>
false</is_3d>
<intensity>
127</intensity>
</GFXVector>
<GFXVector>
<startVertex>
<x>
39.0</x>
<y>
50.0</y>
<z>
0.0</z>
<w>
1.0</w>
<use_x>
true</use_x>
<use_y>
true</use_y>
<use_z>
true</use_z>
<use_w>
true</use_w>
<id>
667060</id>
</startVertex>
<endVertex>
<x>
49.0</x>
<y>
96.0</y>
<z>
0.0</z>
<w>
1.0</w>
<use_x>
true</use_x>
<use_y>
true</use_y>
<use_z>
true</use_z>
<use_w>
true</use_w>
<id>
667062</id>
</endVertex>
<pattern>
255</pattern>
<r>
255</r>
<g>
0</g>
<b>
255</b>
<a>
254</a>
<id>
89282</id>
<order>
3</order>
<start_neighbour_id>
89281</start_neighbour_id>
<end_neighbour_id>
89283</end_neighbour_id>
<start_is_relative>
true</start_is_relative>
<end_is_relative>
true</end_is_relative>
<is_3d>
false</is_3d>
<intensity>
127</intensity>
</GFXVector>
<GFXVector>
<startVertex>
<x>
49.0</x>
<y>
96.0</y>
<z>
0.0</z>
<w>
1.0</w>
<use_x>
true</use_x>
<use_y>
true</use_y>
<use_z>
true</use_z>
<use_w>
true</use_w>
<id>
667062</id>
</startVertex>
<endVertex>
<x>
57.0</x>
<y>
97.0</y>
<z>
0.0</z>
<w>
1.0</w>
<use_x>
true</use_x>
<use_y>
true</use_y>
<use_z>
true</use_z>
<use_w>
true</use_w>
<id>
667064</id>
</endVertex>
<pattern>
0</pattern>
<r>
255</r>
<g>
0</g>
<b>
255</b>
<a>
254</a>
<id>
89283</id>
<order>
4</order>
<start_neighbour_id>
89282</start_neighbour_id>
<end_neighbour_id>
89284</end_neighbour_id>
<start_is_relative>
true</start_is_relative>
<end_is_relative>
true</end_is_relative>
<is_3d>
false</is_3d>
<intensity>
127</intensity>
</GFXVector>
<GFXVector>
<startVertex>
<x>
57.0</x>
<y>
97.0</y>
<z>
0.0</z>
<w>
1.0</w>
<use_x>
true</use_x>
<use_y>
true</use_y>
<use_z>
true</use_z>
<use_w>
true</use_w>
<id>
667064</id>
</startVertex>
<endVertex>
<x>
86.0</x>
<y>
60.0</y>
<z>
0.0</z>
<w>
1.0</w>
<use_x>
true</use_x>
<use_y>
true</use_y>
<use_z>
true</use_z>
<use_w>
true</use_w>
<id>
667066</id>
</endVertex>
<pattern>
255</pattern>
<r>
255</r>
<g>
0</g>
<b>
255</b>
<a>
254</a>
<id>
89284</id>
<order>
5</order>
<start_neighbour_id>
89283</start_neighbour_id>
<end_neighbour_id>
89285</end_neighbour_id>
<start_is_relative>
true</start_is_relative>
<end_is_relative>
true</end_is_relative>
<is_3d>
false</is_3d>
<intensity>
127</intensity>
</GFXVector>
<GFXVector>
<startVertex>
<x>
86.0</x>
<y>
60.0</y>
<z>
0.0</z>
<w>
1.0</w>
<use_x>
true</use_x>
<use_y>
true</use_y>
<use_z>
true</use_z>
<use_w>
true</use_w>
<id>
667066</id>
</startVertex>
<endVertex>
<x>
72.0</x>
<y>
55.0</y>
<z>
0.0</z>
<w>
1.0</w>
<use_x>
true</use_x>
<use_y>
true</use_y>
<use_z>
true</use_z>
<use_w>
true</use_w>
<id>
667068</id>
</endVertex>
<pattern>
255</pattern>
<r>
255</r>
<g>
255</g>
<b>
255</b>
<a>
254</a>
<id>
89285</id>
<order>
6</order>
<start_neighbour_id>
89284</start_neighbour_id>
<end_neighbour_id>
-1</end_neighbour_id>
<start_is_relative>
false</start_is_relative>
<end_is_relative>
false</end_is_relative>
<is_3d>
false</is_3d>
<intensity>
127</intensity>
</GFXVector>
</GFXVectorList>
<GFXVectorList>
<id>
3989</id>
<order>
1</order>
<GFXVector>
<startVertex>
<x>
-84.0</x>
<y>
-4.0</y>
<z>
0.0</z>
<w>
1.0</w>
<use_x>
true</use_x>
<use_y>
true</use_y>
<use_z>
true</use_z>
<use_w>
true</use_w>
<id>
667069</id>
</startVertex>
<endVertex>
<x>
-96.0</x>
<y>
-33.0</y>
<z>
0.0</z>
<w>
1.0</w>
<use_x>
true</use_x>
<use_y>
true</use_y>
<use_z>
true</use_z>
<use_w>
true</use_w>
<id>
667070</id>
</endVertex>
<pattern>
255</pattern>
<r>
255</r>
<g>
255</g>
<b>
255</b>
<a>
254</a>
<id>
89286</id>
<order>
0</order>
<start_neighbour_id>
-1</start_neighbour_id>
<end_neighbour_id>
89287</end_neighbour_id>
<start_is_relative>
false</start_is_relative>
<end_is_relative>
false</end_is_relative>
<is_3d>
false</is_3d>
<intensity>
127</intensity>
</GFXVector>
<GFXVector>
<startVertex>
<x>
-96.0</x>
<y>
-33.0</y>
<z>
0.0</z>
<w>
1.0</w>
<use_x>
true</use_x>
<use_y>
true</use_y>
<use_z>
true</use_z>
<use_w>
true</use_w>
<id>
667070</id>
</startVertex>
<endVertex>
<x>
-177.0</x>
<y>
-72.0</y>
<z>
0.0</z>
<w>
1.0</w>
<use_x>
true</use_x>
<use_y>
true</use_y>
<use_z>
true</use_z>
<use_w>
true</use_w>
<id>
667072</id>
</endVertex>
<pattern>
255</pattern>
<r>
255</r>
<g>
0</g>
<b>
255</b>
<a>
254</a>
<id>
89287</id>
<order>
1</order>
<start_neighbour_id>
89286</start_neighbour_id>
<end_neighbour_id>
89288</end_neighbour_id>
<start_is_relative>
true</start_is_relative>
<end_is_relative>
true</end_is_relative>
<is_3d>
false</is_3d>
<intensity>
127</intensity>
</GFXVector>
<GFXVector>
<startVertex>
<x>
-177.0</x>
<y>
-72.0</y>
<z>
0.0</z>
<w>
1.0</w>
<use_x>
true</use_x>
<use_y>
true</use_y>
<use_z>
true</use_z>
<use_w>
true</use_w>
<id>
667072</id>
</startVertex>
<endVertex>
<x>
-129.0</x>
<y>
-72.0</y>
<z>
0.0</z>
<w>
1.0</w>
<use_x>
true</use_x>
<use_y>
true</use_y>
<use_z>
true</use_z>
<use_w>
true</use_w>
<id>
667074</id>
</endVertex>
<pattern>
255</pattern>
<r>
255</r>
<g>
0</g>
<b>
255</b>
<a>
254</a>
<id>
89288</id>
<order>
2</order>
<start_neighbour_id>
89287</start_neighbour_id>
<end_neighbour_id>
89289</end_neighbour_id>
<start_is_relative>
true</start_is_relative>
<end_is_relative>
true</end_is_relative>
<is_3d>
false</is_3d>
<intensity>
127</intensity>
</GFXVector>
<GFXVector>
<startVertex>
<x>
-129.0</x>
<y>
-72.0</y>
<z>
0.0</z>
<w>
1.0</w>
<use_x>
true</use_x>
<use_y>
true</use_y>
<use_z>
true</use_z>
<use_w>
true</use_w>
<id>
667074</id>
</startVertex>
<endVertex>
<x>
-49.0</x>
<y>
-37.0</y>
<z>
0.0</z>
<w>
1.0</w>
<use_x>
true</use_x>
<use_y>
true</use_y>
<use_z>
true</use_z>
<use_w>
true</use_w>
<id>
667076</id>
</endVertex>
<pattern>
255</pattern>
<r>
255</r>
<g>
0</g>
<b>
255</b>
<a>
254</a>
<id>
89289</id>
<order>
3</order>
<start_neighbour_id>
89288</start_neighbour_id>
<end_neighbour_id>
89290</end_neighbour_id>
<start_is_relative>
true</start_is_relative>
<end_is_relative>
true</end_is_relative>
<is_3d>
false</is_3d>
<intensity>
127</intensity>
</GFXVector>
<GFXVector>
<startVertex>
<x>
-49.0</x>
<y>
-37.0</y>
<z>
0.0</z>
<w>
1.0</w>
<use_x>
true</use_x>
<use_y>
true</use_y>
<use_z>
true</use_z>
<use_w>
true</use_w>
<id>
667076</id>
</startVertex>
<endVertex>
<x>
-46.0</x>
<y>
-28.0</y>
<z>
0.0</z>
<w>
1.0</w>
<use_x>
true</use_x>
<use_y>
true</use_y>
<use_z>
true</use_z>
<use_w>
true</use_w>
<id>
667078</id>
</endVertex>
<pattern>
255</pattern>
<r>
255</r>
<g>
0</g>
<b>
255</b>
<a>
254</a>
<id>
89290</id>
<order>
4</order>
<start_neighbour_id>
89289</start_neighbour_id>
<end_neighbour_id>
89291</end_neighbour_id>
<start_is_relative>
true</start_is_relative>
<end_is_relative>
true</end_is_relative>
<is_3d>
false</is_3d>
<intensity>
127</intensity>
</GFXVector>
<GFXVector>
<startVertex>
<x>
-46.0</x>
<y>
-28.0</y>
<z>
0.0</z>
<w>
1.0</w>
<use_x>
true</use_x>
<use_y>
true</use_y>
<use_z>
true</use_z>
<use_w>
true</use_w>
<id>
667078</id>
</startVertex>
<endVertex>
<x>
4.0</x>
<y>
-28.0</y>
<z>
0.0</z>
<w>
1.0</w>
<use_x>
true</use_x>
<use_y>
true</use_y>
<use_z>
true</use_z>
<use_w>
true</use_w>
<id>
667080</id>
</endVertex>
<pattern>
0</pattern>
<r>
255</r>
<g>
0</g>
<b>
255</b>
<a>
254</a>
<id>
89291</id>
<order>
5</order>
<start_neighbour_id>
89290</start_neighbour_id>
<end_neighbour_id>
89292</end_neighbour_id>
<start_is_relative>
true</start_is_relative>
<end_is_relative>
true</end_is_relative>
<is_3d>
false</is_3d>
<intensity>
127</intensity>
</GFXVector>
<GFXVector>
<startVertex>
<x>
4.0</x>
<y>
-28.0</y>
<z>
0.0</z>
<w>
1.0</w>
<use_x>
true</use_x>
<use_y>
true</use_y>
<use_z>
true</use_z>
<use_w>
true</use_w>
<id>
667080</id>
</startVertex>
<endVertex>
<x>
3.0</x>
<y>
-33.0</y>
<z>
0.0</z>
<w>
1.0</w>
<use_x>
true</use_x>
<use_y>
true</use_y>
<use_z>
true</use_z>
<use_w>
true</use_w>
<id>
667082</id>
</endVertex>
<pattern>
255</pattern>
<r>
255</r>
<g>
0</g>
<b>
255</b>
<a>
254</a>
<id>
89292</id>
<order>
6</order>
<start_neighbour_id>
89291</start_neighbour_id>
<end_neighbour_id>
89293</end_neighbour_id>
<start_is_relative>
true</start_is_relative>
<end_is_relative>
true</end_is_relative>
<is_3d>
false</is_3d>
<intensity>
127</intensity>
</GFXVector>
<GFXVector>
<startVertex>
<x>
3.0</x>
<y>
-33.0</y>
<z>
0.0</z>
<w>
1.0</w>
<use_x>
true</use_x>
<use_y>
true</use_y>
<use_z>
true</use_z>
<use_w>
true</use_w>
<id>
667082</id>
</startVertex>
<endVertex>
<x>
-20.0</x>
<y>
-28.0</y>
<z>
0.0</z>
<w>
1.0</w>
<use_x>
true</use_x>
<use_y>
true</use_y>
<use_z>
true</use_z>
<use_w>
true</use_w>
<id>
667084</id>
</endVertex>
<pattern>
0</pattern>
<r>
255</r>
<g>
0</g>
<b>
255</b>
<a>
254</a>
<id>
89293</id>
<order>
7</order>
<start_neighbour_id>
89292</start_neighbour_id>
<end_neighbour_id>
89294</end_neighbour_id>
<start_is_relative>
true</start_is_relative>
<end_is_relative>
true</end_is_relative>
<is_3d>
false</is_3d>
<intensity>
127</intensity>
</GFXVector>
<GFXVector>
<startVertex>
<x>
-20.0</x>
<y>
-28.0</y>
<z>
0.0</z>
<w>
1.0</w>
<use_x>
true</use_x>
<use_y>
true</use_y>
<use_z>
true</use_z>
<use_w>
true</use_w>
<id>
667084</id>
</startVertex>
<endVertex>
<x>
-28.0</x>
<y>
-39.0</y>
<z>
0.0</z>
<w>
1.0</w>
<use_x>
true</use_x>
<use_y>
true</use_y>
<use_z>
true</use_z>
<use_w>
true</use_w>
<id>
667086</id>
</endVertex>
<pattern>
255</pattern>
<r>
255</r>
<g>
0</g>
<b>
255</b>
<a>
254</a>
<id>
89294</id>
<order>
8</order>
<start_neighbour_id>
89293</start_neighbour_id>
<end_neighbour_id>
89295</end_neighbour_id>
<start_is_relative>
true</start_is_relative>
<end_is_relative>
true</end_is_relative>
<is_3d>
false</is_3d>
<intensity>
127</intensity>
</GFXVector>
<GFXVector>
<startVertex>
<x>
-28.0</x>
<y>
-39.0</y>
<z>
0.0</z>
<w>
1.0</w>
<use_x>
true</use_x>
<use_y>
true</use_y>
<use_z>
true</use_z>
<use_w>
true</use_w>
<id>
667086</id>
</startVertex>
<endVertex>
<x>
-103.0</x>
<y>
-74.0</y>
<z>
0.0</z>
<w>
1.0</w>
<use_x>
true</use_x>
<use_y>
true</use_y>
<use_z>
true</use_z>
<use_w>
true</use_w>
<id>
667088</id>
</endVertex>
<pattern>
255</pattern>
<r>
255</r>
<g>
0</g>
<b>
255</b>
<a>
254</a>
<id>
89295</id>
<order>
9</order>
<start_neighbour_id>
89294</start_neighbour_id>
<end_neighbour_id>
89296</end_neighbour_id>
<start_is_relative>
true</start_is_relative>
<end_is_relative>
true</end_is_relative>
<is_3d>
false</is_3d>
<intensity>
127</intensity>
</GFXVector>
<GFXVector>
<startVertex>
<x>
-103.0</x>
<y>
-74.0</y>
<z>
0.0</z>
<w>
1.0</w>
<use_x>
true</use_x>
<use_y>
true</use_y>
<use_z>
true</use_z>
<use_w>
true</use_w>
<id>
667088</id>
</startVertex>
<endVertex>
<x>
-62.0</x>
<y>
-74.0</y>
<z>
0.0</z>
<w>
1.0</w>
<use_x>
true</use_x>
<use_y>
true</use_y>
<use_z>
true</use_z>
<use_w>
true</use_w>
<id>
667090</id>
</endVertex>
<pattern>
255</pattern>
<r>
255</r>
<g>
0</g>
<b>
255</b>
<a>
254</a>
<id>
89296</id>
<order>
10</order>
<start_neighbour_id>
89295</start_neighbour_id>
<end_neighbour_id>
89297</end_neighbour_id>
<start_is_relative>
true</start_is_relative>
<end_is_relative>
true</end_is_relative>
<is_3d>
false</is_3d>
<intensity>
127</intensity>
</GFXVector>
<GFXVector>
<startVertex>
<x>
-62.0</x>
<y>
-74.0</y>
<z>
0.0</z>
<w>
1.0</w>
<use_x>
true</use_x>
<use_y>
true</use_y>
<use_z>
true</use_z>
<use_w>
true</use_w>
<id>
667090</id>
</startVertex>
<endVertex>
<x>
0.0</x>
<y>
-42.0</y>
<z>
0.0</z>
<w>
1.0</w>
<use_x>
true</use_x>
<use_y>
true</use_y>
<use_z>
true</use_z>
<use_w>
true</use_w>
<id>
667092</id>
</endVertex>
<pattern>
255</pattern>
<r>
255</r>
<g>
0</g>
<b>
255</b>
<a>
254</a>
<id>
89297</id>
<order>
11</order>
<start_neighbour_id>
89296</start_neighbour_id>
<end_neighbour_id>
89298</end_neighbour_id>
<start_is_relative>
true</start_is_relative>
<end_is_relative>
true</end_is_relative>
<is_3d>
false</is_3d>
<intensity>
127</intensity>
</GFXVector>
<GFXVector>
<startVertex>
<x>
0.0</x>
<y>
-42.0</y>
<z>
0.0</z>
<w>
1.0</w>
<use_x>
true</use_x>
<use_y>
true</use_y>
<use_z>
true</use_z>
<use_w>
true</use_w>
<id>
667092</id>
</startVertex>
<endVertex>
<x>
3.0</x>
<y>
-33.0</y>
<z>
0.0</z>
<w>
1.0</w>
<use_x>
true</use_x>
<use_y>
true</use_y>
<use_z>
true</use_z>
<use_w>
true</use_w>
<id>
667094</id>
</endVertex>
<pattern>
255</pattern>
<r>
255</r>
<g>
0</g>
<b>
255</b>
<a>
254</a>
<id>
89298</id>
<order>
12</order>
<start_neighbour_id>
89297</start_neighbour_id>
<end_neighbour_id>
89299</end_neighbour_id>
<start_is_relative>
true</start_is_relative>
<end_is_relative>
true</end_is_relative>
<is_3d>
false</is_3d>
<intensity>
127</intensity>
</GFXVector>
<GFXVector>
<startVertex>
<x>
3.0</x>
<y>
-33.0</y>
<z>
0.0</z>
<w>
1.0</w>
<use_x>
true</use_x>
<use_y>
true</use_y>
<use_z>
true</use_z>
<use_w>
true</use_w>
<id>
667094</id>
</startVertex>
<endVertex>
<x>
8.0</x>
<y>
-31.0</y>
<z>
0.0</z>
<w>
1.0</w>
<use_x>
true</use_x>
<use_y>
true</use_y>
<use_z>
true</use_z>
<use_w>
true</use_w>
<id>
667096</id>
</endVertex>
<pattern>
255</pattern>
<r>
255</r>
<g>
0</g>
<b>
255</b>
<a>
254</a>
<id>
89299</id>
<order>
13</order>
<start_neighbour_id>
89298</start_neighbour_id>
<end_neighbour_id>
89300</end_neighbour_id>
<start_is_relative>
true</start_is_relative>
<end_is_relative>
true</end_is_relative>
<is_3d>
false</is_3d>
<intensity>
127</intensity>
</GFXVector>
<GFXVector>
<startVertex>
<x>
8.0</x>
<y>
-31.0</y>
<z>
0.0</z>
<w>
1.0</w>
<use_x>
true</use_x>
<use_y>
true</use_y>
<use_z>
true</use_z>
<use_w>
true</use_w>
<id>
667096</id>
</startVertex>
<endVertex>
<x>
20.0</x>
<y>
-8.0</y>
<z>
0.0</z>
<w>
1.0</w>
<use_x>
true</use_x>
<use_y>
true</use_y>
<use_z>
true</use_z>
<use_w>
true</use_w>
<id>
667098</id>
</endVertex>
<pattern>
255</pattern>
<r>
255</r>
<g>
255</g>
<b>
255</b>
<a>
254</a>
<id>
89300</id>
<order>
14</order>
<start_neighbour_id>
89299</start_neighbour_id>
<end_neighbour_id>
-1</end_neighbour_id>
<start_is_relative>
false</start_is_relative>
<end_is_relative>
false</end_is_relative>
<is_3d>
false</is_3d>
<intensity>
127</intensity>
</GFXVector>
</GFXVectorList>
</VectorAnimation>
