<GFXVectorList>
<id>
9</id>
<order>
9</order>
<GFXVector>
<startVertex>
<x>
-11.0</x>
<y>
6.0</y>
<z>
0.0</z>
<w>
1.0</w>
<use_x>
true</use_x>
<use_y>
true</use_y>
<use_z>
true</use_z>
<use_w>
true</use_w>
</startVertex>
<endVertex>
<x>
-5.0</x>
<y>
6.0</y>
<z>
0.0</z>
<w>
1.0</w>
<use_x>
true</use_x>
<use_y>
true</use_y>
<use_z>
true</use_z>
<use_w>
true</use_w>
</endVertex>
<pattern>
255</pattern>
<r>
255</r>
<g>
255</g>
<b>
255</b>
<a>
192</a>
<id>
333239</id>
<order>
0</order>
<start_neighbour_id>
-1</start_neighbour_id>
<end_neighbour_id>
333241</end_neighbour_id>
<start_is_relative>
false</start_is_relative>
<end_is_relative>
false</end_is_relative>
<is_3d>
false</is_3d>
<intensity>
96</intensity>
</GFXVector>
<id>
9</id>
<order>
9</order>
<GFXVector>
<startVertex>
<x>
-5.0</x>
<y>
6.0</y>
<z>
0.0</z>
<w>
1.0</w>
<use_x>
true</use_x>
<use_y>
true</use_y>
<use_z>
true</use_z>
<use_w>
true</use_w>
</startVertex>
<endVertex>
<x>
0.0</x>
<y>
6.0</y>
<z>
0.0</z>
<w>
1.0</w>
<use_x>
true</use_x>
<use_y>
true</use_y>
<use_z>
true</use_z>
<use_w>
true</use_w>
</endVertex>
<pattern>
255</pattern>
<r>
255</r>
<g>
0</g>
<b>
255</b>
<a>
192</a>
<id>
333241</id>
<order>
1</order>
<start_neighbour_id>
333239</start_neighbour_id>
<end_neighbour_id>
333243</end_neighbour_id>
<start_is_relative>
true</start_is_relative>
<end_is_relative>
true</end_is_relative>
<is_3d>
false</is_3d>
<intensity>
96</intensity>
</GFXVector>
<id>
9</id>
<order>
9</order>
<GFXVector>
<startVertex>
<x>
0.0</x>
<y>
6.0</y>
<z>
0.0</z>
<w>
1.0</w>
<use_x>
true</use_x>
<use_y>
true</use_y>
<use_z>
true</use_z>
<use_w>
true</use_w>
</startVertex>
<endVertex>
<x>
6.0</x>
<y>
6.0</y>
<z>
0.0</z>
<w>
1.0</w>
<use_x>
true</use_x>
<use_y>
true</use_y>
<use_z>
true</use_z>
<use_w>
true</use_w>
</endVertex>
<pattern>
255</pattern>
<r>
255</r>
<g>
0</g>
<b>
255</b>
<a>
192</a>
<id>
333243</id>
<order>
2</order>
<start_neighbour_id>
333241</start_neighbour_id>
<end_neighbour_id>
333245</end_neighbour_id>
<start_is_relative>
true</start_is_relative>
<end_is_relative>
true</end_is_relative>
<is_3d>
false</is_3d>
<intensity>
96</intensity>
</GFXVector>
<id>
9</id>
<order>
9</order>
<GFXVector>
<startVertex>
<x>
6.0</x>
<y>
6.0</y>
<z>
0.0</z>
<w>
1.0</w>
<use_x>
true</use_x>
<use_y>
true</use_y>
<use_z>
true</use_z>
<use_w>
true</use_w>
</startVertex>
<endVertex>
<x>
11.0</x>
<y>
6.0</y>
<z>
0.0</z>
<w>
1.0</w>
<use_x>
true</use_x>
<use_y>
true</use_y>
<use_z>
true</use_z>
<use_w>
true</use_w>
</endVertex>
<pattern>
255</pattern>
<r>
255</r>
<g>
0</g>
<b>
255</b>
<a>
192</a>
<id>
333245</id>
<order>
3</order>
<start_neighbour_id>
333243</start_neighbour_id>
<end_neighbour_id>
333247</end_neighbour_id>
<start_is_relative>
true</start_is_relative>
<end_is_relative>
true</end_is_relative>
<is_3d>
false</is_3d>
<intensity>
96</intensity>
</GFXVector>
<id>
9</id>
<order>
9</order>
<GFXVector>
<startVertex>
<x>
11.0</x>
<y>
6.0</y>
<z>
0.0</z>
<w>
1.0</w>
<use_x>
true</use_x>
<use_y>
true</use_y>
<use_z>
true</use_z>
<use_w>
true</use_w>
</startVertex>
<endVertex>
<x>
12.0</x>
<y>
2.0</y>
<z>
0.0</z>
<w>
1.0</w>
<use_x>
true</use_x>
<use_y>
true</use_y>
<use_z>
true</use_z>
<use_w>
true</use_w>
</endVertex>
<pattern>
255</pattern>
<r>
255</r>
<g>
0</g>
<b>
255</b>
<a>
192</a>
<id>
333247</id>
<order>
4</order>
<start_neighbour_id>
333245</start_neighbour_id>
<end_neighbour_id>
333249</end_neighbour_id>
<start_is_relative>
true</start_is_relative>
<end_is_relative>
true</end_is_relative>
<is_3d>
false</is_3d>
<intensity>
96</intensity>
</GFXVector>
<id>
9</id>
<order>
9</order>
<GFXVector>
<startVertex>
<x>
12.0</x>
<y>
2.0</y>
<z>
0.0</z>
<w>
1.0</w>
<use_x>
true</use_x>
<use_y>
true</use_y>
<use_z>
true</use_z>
<use_w>
true</use_w>
</startVertex>
<endVertex>
<x>
18.0</x>
<y>
2.0</y>
<z>
0.0</z>
<w>
1.0</w>
<use_x>
true</use_x>
<use_y>
true</use_y>
<use_z>
true</use_z>
<use_w>
true</use_w>
</endVertex>
<pattern>
255</pattern>
<r>
255</r>
<g>
0</g>
<b>
255</b>
<a>
192</a>
<id>
333249</id>
<order>
5</order>
<start_neighbour_id>
333247</start_neighbour_id>
<end_neighbour_id>
333251</end_neighbour_id>
<start_is_relative>
true</start_is_relative>
<end_is_relative>
true</end_is_relative>
<is_3d>
false</is_3d>
<intensity>
96</intensity>
</GFXVector>
<id>
9</id>
<order>
9</order>
<GFXVector>
<startVertex>
<x>
18.0</x>
<y>
2.0</y>
<z>
0.0</z>
<w>
1.0</w>
<use_x>
true</use_x>
<use_y>
true</use_y>
<use_z>
true</use_z>
<use_w>
true</use_w>
</startVertex>
<endVertex>
<x>
19.0</x>
<y>
0.0</y>
<z>
0.0</z>
<w>
1.0</w>
<use_x>
true</use_x>
<use_y>
true</use_y>
<use_z>
true</use_z>
<use_w>
true</use_w>
</endVertex>
<pattern>
255</pattern>
<r>
255</r>
<g>
0</g>
<b>
255</b>
<a>
192</a>
<id>
333251</id>
<order>
6</order>
<start_neighbour_id>
333249</start_neighbour_id>
<end_neighbour_id>
333253</end_neighbour_id>
<start_is_relative>
true</start_is_relative>
<end_is_relative>
true</end_is_relative>
<is_3d>
false</is_3d>
<intensity>
96</intensity>
</GFXVector>
<id>
9</id>
<order>
9</order>
<GFXVector>
<startVertex>
<x>
19.0</x>
<y>
0.0</y>
<z>
0.0</z>
<w>
1.0</w>
<use_x>
true</use_x>
<use_y>
true</use_y>
<use_z>
true</use_z>
<use_w>
true</use_w>
</startVertex>
<endVertex>
<x>
15.0</x>
<y>
-1.0</y>
<z>
0.0</z>
<w>
1.0</w>
<use_x>
true</use_x>
<use_y>
true</use_y>
<use_z>
true</use_z>
<use_w>
true</use_w>
</endVertex>
<pattern>
255</pattern>
<r>
255</r>
<g>
0</g>
<b>
255</b>
<a>
192</a>
<id>
333253</id>
<order>
7</order>
<start_neighbour_id>
333251</start_neighbour_id>
<end_neighbour_id>
333255</end_neighbour_id>
<start_is_relative>
true</start_is_relative>
<end_is_relative>
true</end_is_relative>
<is_3d>
false</is_3d>
<intensity>
96</intensity>
</GFXVector>
<id>
9</id>
<order>
9</order>
<GFXVector>
<startVertex>
<x>
15.0</x>
<y>
-1.0</y>
<z>
0.0</z>
<w>
1.0</w>
<use_x>
true</use_x>
<use_y>
true</use_y>
<use_z>
true</use_z>
<use_w>
true</use_w>
</startVertex>
<endVertex>
<x>
13.0</x>
<y>
-3.0</y>
<z>
0.0</z>
<w>
1.0</w>
<use_x>
true</use_x>
<use_y>
true</use_y>
<use_z>
true</use_z>
<use_w>
true</use_w>
</endVertex>
<pattern>
255</pattern>
<r>
255</r>
<g>
0</g>
<b>
255</b>
<a>
192</a>
<id>
333255</id>
<order>
8</order>
<start_neighbour_id>
333253</start_neighbour_id>
<end_neighbour_id>
333257</end_neighbour_id>
<start_is_relative>
true</start_is_relative>
<end_is_relative>
true</end_is_relative>
<is_3d>
false</is_3d>
<intensity>
96</intensity>
</GFXVector>
<id>
9</id>
<order>
9</order>
<GFXVector>
<startVertex>
<x>
13.0</x>
<y>
-3.0</y>
<z>
0.0</z>
<w>
1.0</w>
<use_x>
true</use_x>
<use_y>
true</use_y>
<use_z>
true</use_z>
<use_w>
true</use_w>
</startVertex>
<endVertex>
<x>
10.0</x>
<y>
-3.0</y>
<z>
0.0</z>
<w>
1.0</w>
<use_x>
true</use_x>
<use_y>
true</use_y>
<use_z>
true</use_z>
<use_w>
true</use_w>
</endVertex>
<pattern>
255</pattern>
<r>
255</r>
<g>
0</g>
<b>
255</b>
<a>
192</a>
<id>
333257</id>
<order>
9</order>
<start_neighbour_id>
333255</start_neighbour_id>
<end_neighbour_id>
333259</end_neighbour_id>
<start_is_relative>
true</start_is_relative>
<end_is_relative>
true</end_is_relative>
<is_3d>
false</is_3d>
<intensity>
96</intensity>
</GFXVector>
<id>
9</id>
<order>
9</order>
<GFXVector>
<startVertex>
<x>
10.0</x>
<y>
-3.0</y>
<z>
0.0</z>
<w>
1.0</w>
<use_x>
true</use_x>
<use_y>
true</use_y>
<use_z>
true</use_z>
<use_w>
true</use_w>
</startVertex>
<endVertex>
<x>
7.0</x>
<y>
-1.0</y>
<z>
0.0</z>
<w>
1.0</w>
<use_x>
true</use_x>
<use_y>
true</use_y>
<use_z>
true</use_z>
<use_w>
true</use_w>
</endVertex>
<pattern>
255</pattern>
<r>
255</r>
<g>
0</g>
<b>
255</b>
<a>
192</a>
<id>
333259</id>
<order>
10</order>
<start_neighbour_id>
333257</start_neighbour_id>
<end_neighbour_id>
333261</end_neighbour_id>
<start_is_relative>
true</start_is_relative>
<end_is_relative>
true</end_is_relative>
<is_3d>
false</is_3d>
<intensity>
96</intensity>
</GFXVector>
<id>
9</id>
<order>
9</order>
<GFXVector>
<startVertex>
<x>
7.0</x>
<y>
-1.0</y>
<z>
0.0</z>
<w>
1.0</w>
<use_x>
true</use_x>
<use_y>
true</use_y>
<use_z>
true</use_z>
<use_w>
true</use_w>
</startVertex>
<endVertex>
<x>
3.0</x>
<y>
0.0</y>
<z>
0.0</z>
<w>
1.0</w>
<use_x>
true</use_x>
<use_y>
true</use_y>
<use_z>
true</use_z>
<use_w>
true</use_w>
</endVertex>
<pattern>
255</pattern>
<r>
255</r>
<g>
0</g>
<b>
255</b>
<a>
192</a>
<id>
333261</id>
<order>
11</order>
<start_neighbour_id>
333259</start_neighbour_id>
<end_neighbour_id>
333263</end_neighbour_id>
<start_is_relative>
true</start_is_relative>
<end_is_relative>
true</end_is_relative>
<is_3d>
false</is_3d>
<intensity>
96</intensity>
</GFXVector>
<id>
9</id>
<order>
9</order>
<GFXVector>
<startVertex>
<x>
3.0</x>
<y>
0.0</y>
<z>
0.0</z>
<w>
1.0</w>
<use_x>
true</use_x>
<use_y>
true</use_y>
<use_z>
true</use_z>
<use_w>
true</use_w>
</startVertex>
<endVertex>
<x>
-3.0</x>
<y>
-1.0</y>
<z>
0.0</z>
<w>
1.0</w>
<use_x>
true</use_x>
<use_y>
true</use_y>
<use_z>
true</use_z>
<use_w>
true</use_w>
</endVertex>
<pattern>
255</pattern>
<r>
255</r>
<g>
0</g>
<b>
255</b>
<a>
192</a>
<id>
333263</id>
<order>
12</order>
<start_neighbour_id>
333261</start_neighbour_id>
<end_neighbour_id>
333265</end_neighbour_id>
<start_is_relative>
true</start_is_relative>
<end_is_relative>
true</end_is_relative>
<is_3d>
false</is_3d>
<intensity>
96</intensity>
</GFXVector>
<id>
9</id>
<order>
9</order>
<GFXVector>
<startVertex>
<x>
-3.0</x>
<y>
-1.0</y>
<z>
0.0</z>
<w>
1.0</w>
<use_x>
true</use_x>
<use_y>
true</use_y>
<use_z>
true</use_z>
<use_w>
true</use_w>
</startVertex>
<endVertex>
<x>
-5.0</x>
<y>
-3.0</y>
<z>
0.0</z>
<w>
1.0</w>
<use_x>
true</use_x>
<use_y>
true</use_y>
<use_z>
true</use_z>
<use_w>
true</use_w>
</endVertex>
<pattern>
255</pattern>
<r>
255</r>
<g>
0</g>
<b>
255</b>
<a>
192</a>
<id>
333265</id>
<order>
13</order>
<start_neighbour_id>
333263</start_neighbour_id>
<end_neighbour_id>
333267</end_neighbour_id>
<start_is_relative>
true</start_is_relative>
<end_is_relative>
true</end_is_relative>
<is_3d>
false</is_3d>
<intensity>
96</intensity>
</GFXVector>
<id>
9</id>
<order>
9</order>
<GFXVector>
<startVertex>
<x>
-5.0</x>
<y>
-3.0</y>
<z>
0.0</z>
<w>
1.0</w>
<use_x>
true</use_x>
<use_y>
true</use_y>
<use_z>
true</use_z>
<use_w>
true</use_w>
</startVertex>
<endVertex>
<x>
-9.0</x>
<y>
-3.0</y>
<z>
0.0</z>
<w>
1.0</w>
<use_x>
true</use_x>
<use_y>
true</use_y>
<use_z>
true</use_z>
<use_w>
true</use_w>
</endVertex>
<pattern>
255</pattern>
<r>
255</r>
<g>
0</g>
<b>
255</b>
<a>
192</a>
<id>
333267</id>
<order>
14</order>
<start_neighbour_id>
333265</start_neighbour_id>
<end_neighbour_id>
333269</end_neighbour_id>
<start_is_relative>
true</start_is_relative>
<end_is_relative>
true</end_is_relative>
<is_3d>
false</is_3d>
<intensity>
96</intensity>
</GFXVector>
<id>
9</id>
<order>
9</order>
<GFXVector>
<startVertex>
<x>
-9.0</x>
<y>
-3.0</y>
<z>
0.0</z>
<w>
1.0</w>
<use_x>
true</use_x>
<use_y>
true</use_y>
<use_z>
true</use_z>
<use_w>
true</use_w>
</startVertex>
<endVertex>
<x>
-11.0</x>
<y>
-1.0</y>
<z>
0.0</z>
<w>
1.0</w>
<use_x>
true</use_x>
<use_y>
true</use_y>
<use_z>
true</use_z>
<use_w>
true</use_w>
</endVertex>
<pattern>
255</pattern>
<r>
255</r>
<g>
0</g>
<b>
255</b>
<a>
192</a>
<id>
333269</id>
<order>
15</order>
<start_neighbour_id>
333267</start_neighbour_id>
<end_neighbour_id>
333271</end_neighbour_id>
<start_is_relative>
true</start_is_relative>
<end_is_relative>
true</end_is_relative>
<is_3d>
false</is_3d>
<intensity>
96</intensity>
</GFXVector>
<id>
9</id>
<order>
9</order>
<GFXVector>
<startVertex>
<x>
-11.0</x>
<y>
-1.0</y>
<z>
0.0</z>
<w>
1.0</w>
<use_x>
true</use_x>
<use_y>
true</use_y>
<use_z>
true</use_z>
<use_w>
true</use_w>
</startVertex>
<endVertex>
<x>
-11.0</x>
<y>
2.0</y>
<z>
0.0</z>
<w>
1.0</w>
<use_x>
true</use_x>
<use_y>
true</use_y>
<use_z>
true</use_z>
<use_w>
true</use_w>
</endVertex>
<pattern>
255</pattern>
<r>
255</r>
<g>
0</g>
<b>
255</b>
<a>
192</a>
<id>
333271</id>
<order>
16</order>
<start_neighbour_id>
333269</start_neighbour_id>
<end_neighbour_id>
333273</end_neighbour_id>
<start_is_relative>
true</start_is_relative>
<end_is_relative>
true</end_is_relative>
<is_3d>
false</is_3d>
<intensity>
96</intensity>
</GFXVector>
<id>
9</id>
<order>
9</order>
<GFXVector>
<startVertex>
<x>
-11.0</x>
<y>
2.0</y>
<z>
0.0</z>
<w>
1.0</w>
<use_x>
true</use_x>
<use_y>
true</use_y>
<use_z>
true</use_z>
<use_w>
true</use_w>
</startVertex>
<endVertex>
<x>
-11.0</x>
<y>
7.0</y>
<z>
0.0</z>
<w>
1.0</w>
<use_x>
true</use_x>
<use_y>
true</use_y>
<use_z>
true</use_z>
<use_w>
true</use_w>
</endVertex>
<pattern>
255</pattern>
<r>
255</r>
<g>
255</g>
<b>
255</b>
<a>
192</a>
<id>
333273</id>
<order>
17</order>
<start_neighbour_id>
333271</start_neighbour_id>
<end_neighbour_id>
-1</end_neighbour_id>
<start_is_relative>
false</start_is_relative>
<end_is_relative>
false</end_is_relative>
<is_3d>
false</is_3d>
<intensity>
96</intensity>
</GFXVector>
</GFXVectorList>
